<?xml version="1.0" encoding="UTF-8"?>
<beans xmlns="http://www.springframework.org/schema/beans"
    xmlns:xsi="http://www.w3.org/2001/XMLSchema-instance"
    xsi:schemaLocation="http://www.springframework.org/schema/beans http://www.springframework.org/schema/beans/spring-beans.xsd">
  <!--  SakaiProxy -->
  <bean id="org.sakaiproject.nssakura.config.logic.SakaiProxy"
    class="org.sakaiproject.nssakura.config.logic.SakaiProxyImpl"
    init-method="init">
    <!-- API injection -->
    <property name="securityService" ref="org.sakaiproject.authz.api.SecurityService" />
    <property name="sessionManager" ref="org.sakaiproject.tool.api.SessionManager" />
    <property name="toolManager" ref="org.sakaiproject.tool.api.ToolManager" />
    <property name="userDirectoryService" ref="org.sakaiproject.user.api.UserDirectoryService" />
    <property name="eventTrackingService" ref="org.sakaiproject.event.api.EventTrackingService" />
    <property name="serverConfigurationService" ref="org.sakaiproject.component.api.ServerConfigurationService" />
    <property name="siteService" ref="org.sakaiproject.site.api.SiteService" />
  </bean>

  <!-- setup a DAO, accessed via the transaction proxy -->
  <bean
    id="org.sakaiproject.nssakura.config.dao.NSConfigDaoTarget"
    class="org.sakaiproject.nssakura.config.dao.NSConfigDaoImpl"
    init-method="init">
    <property name="sessionFactory" ref="org.sakaiproject.springframework.orm.hibernate.GlobalSessionFactory" />
  </bean>

  <!--  register the DAO as a transactional interceptor. Use the classloader proxy from gendao because this is a protected DAO -->
  <bean
    id="org.sakaiproject.nssakura.config.dao.NSConfigDao"
    class="org.sakaiproject.genericdao.springutil.CurrentClassLoaderTxProxyFactoryBean">
    <property name="transactionManager" ref="org.sakaiproject.springframework.orm.hibernate.GlobalTransactionManager" />
    <property name="target" ref="org.sakaiproject.nssakura.config.dao.NSConfigDaoTarget" />
    <property name="transactionAttributes">
      <props>
        <prop key="*">PROPAGATION_REQUIRED</prop>
      </props>
    </property>
  </bean>

  <!-- ProjectLogic -->
  <bean id="org.sakaiproject.nssakura.config.logic.ProjectLogic"
    class="org.sakaiproject.nssakura.config.logic.ProjectLogicImpl"
    init-method="init">
    <property name="nsConfigDao" ref="org.sakaiproject.nssakura.config.dao.NSConfigDao" />
  </bean>

  <!-- Add our HBM files to the Sakai global session factory -->
  <bean
    id="org.sakaiproject.nssakura.config.hbm.HBMMappingList"
    class="org.sakaiproject.springframework.orm.hibernate.impl.AdditionalHibernateMappingsImpl">
    <property name="mappingResources">
      <list>
        <value>org/sakaiproject/nssakura/config/hbm/NSConfig.hbm.xml</value>
      </list>
    </property>
  </bean>

  <!-- NSConfigurationService facade -->
  <bean
    id="org.sakaiproject.nssakura.config.api.NSConfigurationService"
    class="org.sakaiproject.nssakura.config.api.impl.NSConfigurationServiceImpl">
    <property name="nsConfigDao" ref="org.sakaiproject.nssakura.config.dao.NSConfigDao" />
  </bean>
</beans>
